.gitignore
README.rst
setup.cfg
setup.py
collective/__init__.py
collective.portletalias.egg-info/PKG-INFO
collective.portletalias.egg-info/SOURCES.txt
collective.portletalias.egg-info/dependency_links.txt
collective.portletalias.egg-info/entry_points.txt
collective.portletalias.egg-info/namespace_packages.txt
collective.portletalias.egg-info/not-zip-safe
collective.portletalias.egg-info/paster_plugins.txt
collective.portletalias.egg-info/requires.txt
collective.portletalias.egg-info/top_level.txt
collective/portletalias/__init__.py
collective/portletalias/configure.zcml
collective/portletalias/portlet-data.pt
collective/portletalias/tests.py
collective/portletalias/utils.py
collective/portletalias/views.py
collective/portletalias/portlets/__init__.py
collective/portletalias/portlets/aliasportlet.py
collective/portletalias/portlets/configure.zcml
collective/portletalias/profiles/default/metadata.xml
collective/portletalias/profiles/default/portlets.xml
collective/portletalias/tests/__init__.py
collective/portletalias/tests/base_aliasportlet.py
collective/portletalias/tests/test_aliasportlet.py
docs/HISTORY.txt
docs/INSTALL.txt
docs/LICENSE.GPL
docs/LICENSE.txt